phoenixia/ModelingHannibal.py
phoenixia/__init__.py
phoenixia-0.0.2.dist-info/LICENSE
phoenixia-0.0.2.dist-info/METADATA
phoenixia-0.0.2.dist-info/WHEEL
phoenixia-0.0.2.dist-info/top_level.txt
phoenixia-0.0.2.dist-info/RECORD
