Metadata-Version: 2.1
Name: phoenixia
Version: 0.0.2
Summary: a repository for Phoenix-IA models
Home-page: https://github.com/not-lain/phoenixia
License: Apache 2.0 License
Classifier: Intended Audience :: Developers
Classifier: Intended Audience :: Education
Classifier: Intended Audience :: Science/Research
Classifier: License :: OSI Approved :: Apache Software License
Classifier: Programming Language :: Python :: 3.9
Classifier: Topic :: Scientific/Engineering :: Artificial Intelligence
License-File: LICENSE
Requires-Dist: setuptools >=42
Requires-Dist: wheel >=0.37
Requires-Dist: torch >=2.2.1
Requires-Dist: huggingface-hub >=0.22
